setup.py
HUIlib/__init__.py
HUIlib/one.py
HUIlib/two.py
HUIlib.egg-info/PKG-INFO
HUIlib.egg-info/SOURCES.txt
HUIlib.egg-info/dependency_links.txt
HUIlib.egg-info/top_level.txt